<?xml version='1.0' encoding='UTF-8'?>
<hsf>
    <group id="mobius_dev">
        <!--************* store begin ***********-->
        <!-- ************* sys store *********** -->
        <consumer id="sysTradeStoreConsumer" interface="com.mobius.providers.store.sys.SysTradeStore"
                  version="for-dev" clientTimeout="5000">
        </consumer>

        <consumer id="sysIpServerStoreConsumer" interface="com.mobius.providers.store.sys.SysIpServerStore"
                  version="for-dev" clientTimeout="5000">
        </consumer>

        <!-- ************* futures store *********** -->
        <consumer id="futuresSymbolStoreConsumer" interface="com.mobius.providers.store.futures.FuturesSymbolStore"
                  version="for-dev" clientTimeout="5000">
        </consumer>

        <consumer id="futuresDailyUsdtStoreConsumer" interface="com.mobius.providers.store.futures.FuturesDailyUsdtStore"
                  version="for-dev" clientTimeout="5000">
        </consumer>


        <consumer id="futuresDailyBtcStoreConsumer" interface="com.mobius.providers.store.futures.FuturesDailyBtcStore"
                  version="for-dev" clientTimeout="5000">
        </consumer>


        <consumer id="futuresDailyEthStoreConsumer" interface="com.mobius.providers.store.futures.FuturesDailyEthStore"
                  version="for-dev" clientTimeout="5000">
        </consumer>

        
        
        <consumer id="futuresDetailUsdtOkexStoreConsumer"
                  interface="com.mobius.providers.store.futures.FuturesDetailUsdtOkexStore"
                  version="for-dev" clientTimeout="5000">
        </consumer>


        <consumer id="futuresDetailBtcOkexStoreConsumer"
                  interface="com.mobius.providers.store.futures.FuturesDetailBtcOkexStore"
                  version="for-dev" clientTimeout="5000">
        </consumer>


        <consumer id="futuresDetailEthOkexStoreConsumer"
                  interface="com.mobius.providers.store.futures.FuturesDetailEthOkexStore"
                  version="for-dev" clientTimeout="5000">
        </consumer>


        <consumer id="futuresDetailUsdtBitmexStoreConsumer"
                  interface="com.mobius.providers.store.futures.FuturesDetailUsdtBitmexStore"
                  version="for-dev" clientTimeout="5000">
        </consumer>
        

        <!-- ************* spot store *********** -->
        <consumer id="spotSymbolStoreConsumer" interface="com.mobius.providers.store.spot.SpotSymbolStore"
                  version="for-dev" clientTimeout="5000">
        </consumer>

        <consumer id="spotDailyUsdtStoreConsumer" interface="com.mobius.providers.store.spot.SpotDailyUsdtStore"
                  version="for-dev" clientTimeout="5000">
        </consumer>


        <consumer id="spotDailyBtcStoreConsumer" interface="com.mobius.providers.store.spot.SpotDailyBtcStore"
                  version="for-dev" clientTimeout="5000">
        </consumer>


        <consumer id="spotDailyEthStoreConsumer" interface="com.mobius.providers.store.spot.SpotDailyEthStore"
                  version="for-dev" clientTimeout="5000">
        </consumer>

        
        
        <consumer id="spotDetailUsdtOkexStoreConsumer" interface="com.mobius.providers.store.spot.SpotDetailUsdtOkexStore"
                  version="for-dev" clientTimeout="5000">
        </consumer>


        <consumer id="spotDetailBtcOkexStoreConsumer" interface="com.mobius.providers.store.spot.SpotDetailBtcOkexStore"
                  version="for-dev" clientTimeout="5000">
        </consumer>


        <consumer id="spotDetailEthOkexStoreConsumer" interface="com.mobius.providers.store.spot.SpotDetailEthOkexStore"
                  version="for-dev" clientTimeout="5000">
        </consumer>
        
        

        <consumer id="spotDetailUsdtHuobiStoreConsumer" interface="com.mobius.providers.store.spot.SpotDetailUsdtHuobiStore"
                  version="for-dev" clientTimeout="5000">
        </consumer>


        <consumer id="spotDetailBtcHuobiStoreConsumer" interface="com.mobius.providers.store.spot.SpotDetailBtcHuobiStore"
                  version="for-dev" clientTimeout="5000">
        </consumer>


        <consumer id="spotDetailEthHuobiStoreConsumer" interface="com.mobius.providers.store.spot.SpotDetailEthHuobiStore"
                  version="for-dev" clientTimeout="5000">
        </consumer>

        
        

        <consumer id="spotDetailUsdtBinanceStoreConsumer" interface="com.mobius.providers.store.spot.SpotDetailUsdtBinanceStore"
                  version="for-dev" clientTimeout="5000">
        </consumer>


        <consumer id="spotDetailBtcBinanceStoreConsumer" interface="com.mobius.providers.store.spot.SpotDetailBtcBinanceStore"
                  version="for-dev" clientTimeout="5000">
        </consumer>


        <consumer id="spotDetailEthBinanceStoreConsumer" interface="com.mobius.providers.store.spot.SpotDetailEthBinanceStore"
                  version="for-dev" clientTimeout="5000">
        </consumer>

        

        <consumer id="spotDetailUsdtBitfinexStoreConsumer" interface="com.mobius.providers.store.spot.SpotDetailUsdtBitfinexStore"
                  version="for-dev" clientTimeout="5000">
        </consumer>


        <consumer id="spotDetailBtcBitfinexStoreConsumer" interface="com.mobius.providers.store.spot.SpotDetailBtcBitfinexStore"
                  version="for-dev" clientTimeout="5000">
        </consumer>


        <consumer id="spotDetailEthBitfinexStoreConsumer" interface="com.mobius.providers.store.spot.SpotDetailEthBitfinexStore"
                  version="for-dev" clientTimeout="5000">
        </consumer>
    </group>

</hsf>